mediaf.py
setup.py
mediaf.egg-info/PKG-INFO
mediaf.egg-info/SOURCES.txt
mediaf.egg-info/dependency_links.txt
mediaf.egg-info/top_level.txt