Metadata-Version: 1.1
Name: mediaf
Version: 1
Summary: pip install mediaf
Home-page: https://github.com/RashadGarayev/mediaf
Author: Rashad Garayev
Author-email: pythonaz@yahoo.com
License: MIT
Keywords: mediaf
Platform: UNKNOWN
Classifier: Development Status :: 3 - Alpha
Classifier: Intended Audience :: Developers
Classifier: Topic :: Software Development :: Build Tools
Classifier: License :: OSI Approved :: MIT License
Classifier: Programming Language :: Python :: 2
Classifier: Programming Language :: Python :: 2.6
Classifier: Programming Language :: Python :: 2.7
